setup.py
EasyPysion/Engine.py
EasyPysion/__init__.py
EasyPysion.egg-info/PKG-INFO
EasyPysion.egg-info/SOURCES.txt
EasyPysion.egg-info/dependency_links.txt
EasyPysion.egg-info/top_level.txt